{
  "$schema": "https://developer.microsoft.com/json-schemas/fabric/item/report/definition/visualContainer/2.9.0/schema.json",
  "name": "bfb990934bba4364216f",
  "position": {
    "x": 0,
    "y": 511.25,
    "z": 1001,
    "height": 208.75,
    "width": 1280,
    "tabOrder": 0
  },
  "visual": {
    "visualType": "lineChart",
    "query": {
      "queryState": {
        "Category": {
          "projections": [
            {
              "field": {
                "HierarchyLevel": {
                  "Expression": {
                    "Hierarchy": {
                      "Expression": {
                        "PropertyVariationSource": {
                          "Expression": {
                            "SourceRef": {
                              "Entity": "dim_date"
                            }
                          },
                          "Name": "Variation",
                          "Property": "full_date"
                        }
                      },
                      "Hierarchy": "Date Hierarchy"
                    }
                  },
                  "Level": "Year"
                }
              },
              "queryRef": "dim_date.full_date.Variation.Date Hierarchy.Year",
              "nativeQueryRef": "full_date Year",
              "active": true
            },
            {
              "field": {
                "HierarchyLevel": {
                  "Expression": {
                    "Hierarchy": {
                      "Expression": {
                        "PropertyVariationSource": {
                          "Expression": {
                            "SourceRef": {
                              "Entity": "dim_date"
                            }
                          },
                          "Name": "Variation",
                          "Property": "full_date"
                        }
                      },
                      "Hierarchy": "Date Hierarchy"
                    }
                  },
                  "Level": "Quarter"
                }
              },
              "queryRef": "dim_date.full_date.Variation.Date Hierarchy.Quarter",
              "nativeQueryRef": "full_date Quarter",
              "active": true
            },
            {
              "field": {
                "HierarchyLevel": {
                  "Expression": {
                    "Hierarchy": {
                      "Expression": {
                        "PropertyVariationSource": {
                          "Expression": {
                            "SourceRef": {
                              "Entity": "dim_date"
                            }
                          },
                          "Name": "Variation",
                          "Property": "full_date"
                        }
                      },
                      "Hierarchy": "Date Hierarchy"
                    }
                  },
                  "Level": "Month"
                }
              },
              "queryRef": "dim_date.full_date.Variation.Date Hierarchy.Month",
              "nativeQueryRef": "full_date Month",
              "active": true
            },
            {
              "field": {
                "HierarchyLevel": {
                  "Expression": {
                    "Hierarchy": {
                      "Expression": {
                        "PropertyVariationSource": {
                          "Expression": {
                            "SourceRef": {
                              "Entity": "dim_date"
                            }
                          },
                          "Name": "Variation",
                          "Property": "full_date"
                        }
                      },
                      "Hierarchy": "Date Hierarchy"
                    }
                  },
                  "Level": "Day"
                }
              },
              "queryRef": "dim_date.full_date.Variation.Date Hierarchy.Day",
              "nativeQueryRef": "full_date Day",
              "active": false
            }
          ]
        },
        "Y": {
          "projections": [
            {
              "field": {
                "Measure": {
                  "Expression": {
                    "SourceRef": {
                      "Entity": "01_SalesMeasures"
                    }
                  },
                  "Property": "Realized Revenue"
                }
              },
              "queryRef": "01_SalesMeasures.Realized Revenue",
              "nativeQueryRef": "Realized Revenue"
            },
            {
              "field": {
                "Measure": {
                  "Expression": {
                    "SourceRef": {
                      "Entity": "01_SalesMeasures"
                    }
                  },
                  "Property": "Lost Revenue"
                }
              },
              "queryRef": "01_SalesMeasures.Lost Revenue",
              "nativeQueryRef": "Lost Revenue"
            }
          ]
        }
      }
    },
    "objects": {
      "legend": [
        {
          "properties": {
            "position": {
              "expr": {
                "Literal": {
                  "Value": "'Top'"
                }
              }
            },
            "fontSize": {
              "expr": {
                "Literal": {
                  "Value": "11D"
                }
              }
            }
          }
        }
      ],
      "lineStyles": [
        {
          "properties": {
            "lineStyle": {
              "expr": {
                "Literal": {
                  "Value": "'solid'"
                }
              }
            },
            "strokeLineJoin": {
              "expr": {
                "Literal": {
                  "Value": "'round'"
                }
              }
            },
            "lineChartType": {
              "expr": {
                "Literal": {
                  "Value": "'linear'"
                }
              }
            },
            "interpolationSmooth": {
              "expr": {
                "Literal": {
                  "Value": "'monotoneX'"
                }
              }
            },
            "interpolationSmoothParam": {
              "expr": {
                "Literal": {
                  "Value": "0D"
                }
              }
            },
            "strokeWidth": {
              "expr": {
                "Literal": {
                  "Value": "3D"
                }
              }
            }
          }
        }
      ]
    },
    "visualContainerObjects": {
      "title": [
        {
          "properties": {
            "text": {
              "expr": {
                "Literal": {
                  "Value": "'Revenue Trend'"
                }
              }
            },
            "fontSize": {
              "expr": {
                "Literal": {
                  "Value": "15D"
                }
              }
            }
          }
        }
      ]
    },
    "drillFilterOtherVisuals": true
  }
}