{
  "$schema": "https://developer.microsoft.com/json-schemas/fabric/item/report/definition/bookmark/2.1.0/schema.json",
  "displayName": "Open Nav Bar - Revenue Drivers (P)",
  "name": "779a050b3b5d4db58ee84c0412ca7222",
  "options": {
    "targetVisualNames": [
      "6b3bbdd5a001d872900e",
      "f7710f9506b69d603867",
      "6bd85a4e0b5bb4609767",
      "37672ab7abc86d221036",
      "3c33159bbcd433b20003",
      "02a591eb35967c845e04",
      "03d14ba3b30d83b834bc",
      "4180f81623797094be93",
      "507dda986c36079356b4",
      "6a9f431d510c34cebcb1",
      "8302f5a0d1bb19c1485e",
      "876dc6904a900ab23620",
      "90aa75f791a61b944800",
      "948ef9ac10b1b0021dee",
      "bdd2870b100a10b6806d",
      "ce38fb7a65e7d959a94d",
      "d5c9948f35390285200c",
      "92266a57ec3159645018",
      "b015c3ebd9bb65dc070b",
      "0f040b7da17690c5a902",
      "1b2f3823a42db5ce892e",
      "2c5f09e0abe1ca45eb98",
      "409472c4aa0e50a82516",
      "4e39ff7f5d1adcd83cc5",
      "50389e3c01e484715e7e",
      "654cc84405b2b2005dd5",
      "6cf8ec01b53da1738ec0",
      "9db7eba015d54a98de02",
      "ac9be94fa60441abbc71",
      "b1acb1b51542472142d5",
      "fcdbd8250abce6adda06",
      "e81c175be5e45c77de0c",
      "12c99e420d68a7452ee7",
      "dbf5dae230d780d8ca36"
    ],
    "suppressActiveSection": true,
    "suppressData": true
  },
  "explorationState": {
    "version": "1.3",
    "activeSection": "71a28e25769e8f842b35",
    "sections": {
      "71a28e25769e8f842b35": {
        "visualContainers": {
          "02a591eb35967c845e04": {
            "singleVisual": {
              "visualType": "actionButton",
              "objects": {}
            }
          },
          "03d14ba3b30d83b834bc": {
            "singleVisual": {
              "visualType": "actionButton",
              "objects": {}
            }
          },
          "0f040b7da17690c5a902": {
            "singleVisual": {
              "visualType": "actionButton",
              "objects": {}
            }
          },
          "12c99e420d68a7452ee7": {
            "singleVisual": {
              "visualType": "shape",
              "objects": {}
            }
          },
          "1b2f3823a42db5ce892e": {
            "singleVisual": {
              "visualType": "actionButton",
              "objects": {}
            }
          },
          "2c5f09e0abe1ca45eb98": {
            "singleVisual": {
              "visualType": "actionButton",
              "objects": {}
            }
          },
          "37672ab7abc86d221036": {
            "singleVisual": {
              "visualType": "actionButton",
              "objects": {}
            }
          },
          "3eb5a0cb426906e05938": {
            "filters": {
              "byExpr": [
                {
                  "name": "2a05d579ba9ee3518c94",
                  "type": "Advanced",
                  "expression": {
                    "Measure": {
                      "Expression": {
                        "SourceRef": {
                          "Entity": "01_SalesMeasures"
                        }
                      },
                      "Property": "Completed Orders"
                    }
                  },
                  "howCreated": 0
                },
                {
                  "name": "09c35b389847bc212dd6",
                  "type": "Advanced",
                  "expression": {
                    "Measure": {
                      "Expression": {
                        "SourceRef": {
                          "Entity": "01_SalesMeasures"
                        }
                      },
                      "Property": "Realized Revenue"
                    }
                  },
                  "howCreated": 0
                },
                {
                  "name": "afe07b7306b17909d4c6",
                  "type": "Advanced",
                  "expression": {
                    "Measure": {
                      "Expression": {
                        "SourceRef": {
                          "Entity": "01_SalesMeasures"
                        }
                      },
                      "Property": "Product Count"
                    }
                  },
                  "howCreated": 0
                },
                {
                  "name": "2bf9c500e50398cae3a7",
                  "type": "Advanced",
                  "expression": {
                    "Measure": {
                      "Expression": {
                        "SourceRef": {
                          "Entity": "01_SalesMeasures"
                        }
                      },
                      "Property": "Total Quantity"
                    }
                  },
                  "howCreated": 0
                },
                {
                  "name": "da988fef1be257e56006",
                  "type": "Advanced",
                  "expression": {
                    "Measure": {
                      "Expression": {
                        "SourceRef": {
                          "Entity": "01_SalesMeasures"
                        }
                      },
                      "Property": "Average Unit Price"
                    }
                  },
                  "howCreated": 0
                },
                {
                  "name": "98f02873ca69805c87cb",
                  "type": "Advanced",
                  "expression": {
                    "Measure": {
                      "Expression": {
                        "SourceRef": {
                          "Entity": "01_SalesMeasures"
                        }
                      },
                      "Property": "Average Quantity per Order"
                    }
                  },
                  "howCreated": 0
                }
              ]
            },
            "singleVisual": {
              "visualType": "cardVisual",
              "objects": {},
              "orderBy": [
                {
                  "Direction": 2,
                  "Expression": {
                    "Measure": {
                      "Expression": {
                        "SourceRef": {
                          "Entity": "01_SalesMeasures"
                        }
                      },
                      "Property": "Completed Orders"
                    }
                  }
                }
              ]
            }
          },
          "409472c4aa0e50a82516": {
            "singleVisual": {
              "visualType": "actionButton",
              "objects": {}
            }
          },
          "4180f81623797094be93": {
            "singleVisual": {
              "visualType": "actionButton",
              "objects": {}
            }
          },
          "4e39ff7f5d1adcd83cc5": {
            "singleVisual": {
              "visualType": "actionButton",
              "objects": {}
            }
          },
          "50389e3c01e484715e7e": {
            "singleVisual": {
              "visualType": "actionButton",
              "objects": {}
            }
          },
          "507dda986c36079356b4": {
            "singleVisual": {
              "visualType": "actionButton",
              "objects": {}
            }
          },
          "654cc84405b2b2005dd5": {
            "singleVisual": {
              "visualType": "actionButton",
              "objects": {}
            }
          },
          "6a9f431d510c34cebcb1": {
            "singleVisual": {
              "visualType": "actionButton",
              "objects": {}
            }
          },
          "6cf8ec01b53da1738ec0": {
            "singleVisual": {
              "visualType": "image",
              "objects": {}
            }
          },
          "8302f5a0d1bb19c1485e": {
            "singleVisual": {
              "visualType": "actionButton",
              "objects": {}
            }
          },
          "8599e4dff9c4045f7223": {
            "singleVisual": {
              "visualType": "textbox",
              "objects": {}
            }
          },
          "876dc6904a900ab23620": {
            "singleVisual": {
              "visualType": "actionButton",
              "objects": {}
            }
          },
          "90aa75f791a61b944800": {
            "singleVisual": {
              "visualType": "actionButton",
              "objects": {}
            }
          },
          "92266a57ec3159645018": {
            "singleVisual": {
              "visualType": "image",
              "objects": {}
            }
          },
          "948ef9ac10b1b0021dee": {
            "singleVisual": {
              "visualType": "actionButton",
              "objects": {}
            }
          },
          "9db7eba015d54a98de02": {
            "singleVisual": {
              "visualType": "actionButton",
              "objects": {}
            }
          },
          "aa39682ba7399c85f960": {
            "filters": {
              "byExpr": [
                {
                  "name": "bf8dbb20a19405709c63",
                  "type": "Categorical",
                  "expression": {
                    "Column": {
                      "Expression": {
                        "SourceRef": {
                          "Entity": "dim_product"
                        }
                      },
                      "Property": "product_name"
                    }
                  },
                  "howCreated": 0
                },
                {
                  "name": "1bf65abb45017077a8b2",
                  "type": "Advanced",
                  "expression": {
                    "Aggregation": {
                      "Expression": {
                        "Column": {
                          "Expression": {
                            "SourceRef": {
                              "Entity": "dim_product"
                            }
                          },
                          "Property": "product_list_price"
                        }
                      },
                      "Function": 0
                    }
                  },
                  "howCreated": 0
                },
                {
                  "name": "bdf99ba2384e7b008ab3",
                  "type": "Advanced",
                  "expression": {
                    "Measure": {
                      "Expression": {
                        "SourceRef": {
                          "Entity": "01_SalesMeasures"
                        }
                      },
                      "Property": "Total Quantity"
                    }
                  },
                  "howCreated": 0
                },
                {
                  "name": "fcb650d2c1e177b03ce0",
                  "type": "Advanced",
                  "expression": {
                    "Measure": {
                      "Expression": {
                        "SourceRef": {
                          "Entity": "01_SalesMeasures"
                        }
                      },
                      "Property": "Realized Revenue"
                    }
                  },
                  "howCreated": 0
                },
                {
                  "name": "bba914bfdd7534589a40",
                  "type": "Advanced",
                  "expression": {
                    "Measure": {
                      "Expression": {
                        "SourceRef": {
                          "Entity": "01_SalesMeasures"
                        }
                      },
                      "Property": "Contribution %"
                    }
                  },
                  "howCreated": 0
                },
                {
                  "name": "45177a9b372c21708a25",
                  "type": "Advanced",
                  "expression": {
                    "Measure": {
                      "Expression": {
                        "SourceRef": {
                          "Entity": "01_SalesMeasures"
                        }
                      },
                      "Property": "Cumulative %"
                    }
                  },
                  "howCreated": 0
                }
              ]
            },
            "singleVisual": {
              "visualType": "tableEx",
              "objects": {},
              "orderBy": [
                {
                  "Direction": 2,
                  "Expression": {
                    "Measure": {
                      "Expression": {
                        "SourceRef": {
                          "Entity": "01_SalesMeasures"
                        }
                      },
                      "Property": "Realized Revenue"
                    }
                  }
                }
              ]
            }
          },
          "ac9be94fa60441abbc71": {
            "singleVisual": {
              "visualType": "actionButton",
              "objects": {}
            }
          },
          "b1acb1b51542472142d5": {
            "singleVisual": {
              "visualType": "actionButton",
              "objects": {}
            }
          },
          "bdd2870b100a10b6806d": {
            "singleVisual": {
              "visualType": "image",
              "objects": {}
            }
          },
          "cc3202ccc24b4258425b": {
            "filters": {
              "byExpr": [
                {
                  "name": "000b666be7888bbc3d93",
                  "type": "Advanced",
                  "expression": {
                    "Measure": {
                      "Expression": {
                        "SourceRef": {
                          "Entity": "Last Refresh"
                        }
                      },
                      "Property": "Last Refresh"
                    }
                  },
                  "howCreated": 0
                }
              ]
            },
            "singleVisual": {
              "visualType": "cardVisual",
              "objects": {}
            }
          },
          "ce38fb7a65e7d959a94d": {
            "singleVisual": {
              "visualType": "actionButton",
              "objects": {}
            }
          },
          "d28fbbbe81b2db684536": {
            "filters": {
              "byExpr": [
                {
                  "name": "dac2a5e3444b0aa7eaf3",
                  "type": "TopN",
                  "filter": {
                    "Version": 2,
                    "From": [
                      {
                        "Name": "subquery",
                        "Expression": {
                          "Subquery": {
                            "Query": {
                              "Version": 2,
                              "From": [
                                {
                                  "Name": "0",
                                  "Entity": "01_SalesMeasures",
                                  "Type": 0
                                },
                                {
                                  "Name": "d",
                                  "Entity": "dim_product",
                                  "Type": 0
                                }
                              ],
                              "Select": [
                                {
                                  "Column": {
                                    "Expression": {
                                      "SourceRef": {
                                        "Source": "d"
                                      }
                                    },
                                    "Property": "product_name"
                                  },
                                  "Name": "field"
                                }
                              ],
                              "OrderBy": [
                                {
                                  "Direction": 2,
                                  "Expression": {
                                    "Measure": {
                                      "Expression": {
                                        "SourceRef": {
                                          "Source": "0"
                                        }
                                      },
                                      "Property": "Realized Revenue"
                                    }
                                  }
                                }
                              ],
                              "Top": 20
                            }
                          }
                        },
                        "Type": 2
                      },
                      {
                        "Name": "d",
                        "Entity": "dim_product",
                        "Type": 0
                      }
                    ],
                    "Where": [
                      {
                        "Condition": {
                          "In": {
                            "Expressions": [
                              {
                                "Column": {
                                  "Expression": {
                                    "SourceRef": {
                                      "Source": "d"
                                    }
                                  },
                                  "Property": "product_name"
                                }
                              }
                            ],
                            "Table": {
                              "SourceRef": {
                                "Source": "subquery"
                              }
                            }
                          }
                        }
                      }
                    ]
                  },
                  "expression": {
                    "Column": {
                      "Expression": {
                        "SourceRef": {
                          "Entity": "dim_product"
                        }
                      },
                      "Property": "product_name"
                    }
                  },
                  "howCreated": 0
                },
                {
                  "name": "91410f62a5a6e1782a0a",
                  "type": "Advanced",
                  "expression": {
                    "Measure": {
                      "Expression": {
                        "SourceRef": {
                          "Entity": "01_SalesMeasures"
                        }
                      },
                      "Property": "Realized Revenue"
                    }
                  },
                  "howCreated": 0
                }
              ]
            },
            "singleVisual": {
              "visualType": "barChart",
              "objects": {},
              "orderBy": [
                {
                  "Direction": 2,
                  "Expression": {
                    "Measure": {
                      "Expression": {
                        "SourceRef": {
                          "Entity": "01_SalesMeasures"
                        }
                      },
                      "Property": "Realized Revenue"
                    }
                  }
                }
              ],
              "activeProjections": {
                "Category": [
                  {
                    "Column": {
                      "Expression": {
                        "SourceRef": {
                          "Entity": "dim_product"
                        }
                      },
                      "Property": "product_name"
                    }
                  }
                ]
              }
            }
          },
          "d5c9948f35390285200c": {
            "singleVisual": {
              "visualType": "actionButton",
              "objects": {}
            }
          },
          "db5852932c9a55b99ca6": {
            "filters": {
              "byExpr": [
                {
                  "name": "f3980515670e38e372b6",
                  "type": "Categorical",
                  "expression": {
                    "Column": {
                      "Expression": {
                        "SourceRef": {
                          "Entity": "dim_product"
                        }
                      },
                      "Property": "categ_name"
                    }
                  },
                  "howCreated": 0
                },
                {
                  "name": "9338e1374b03424d8a9a",
                  "type": "Advanced",
                  "expression": {
                    "Measure": {
                      "Expression": {
                        "SourceRef": {
                          "Entity": "01_SalesMeasures"
                        }
                      },
                      "Property": "Realized Revenue"
                    }
                  },
                  "howCreated": 0
                }
              ]
            },
            "singleVisual": {
              "visualType": "clusteredColumnChart",
              "objects": {},
              "orderBy": [
                {
                  "Direction": 2,
                  "Expression": {
                    "Measure": {
                      "Expression": {
                        "SourceRef": {
                          "Entity": "01_SalesMeasures"
                        }
                      },
                      "Property": "Realized Revenue"
                    }
                  }
                }
              ],
              "activeProjections": {
                "Category": [
                  {
                    "Column": {
                      "Expression": {
                        "SourceRef": {
                          "Entity": "dim_product"
                        }
                      },
                      "Property": "categ_name"
                    }
                  }
                ]
              }
            }
          },
          "dbf5dae230d780d8ca36": {
            "singleVisual": {
              "visualType": "image",
              "objects": {}
            }
          },
          "e81c175be5e45c77de0c": {
            "singleVisual": {
              "visualType": "shape",
              "objects": {}
            }
          },
          "f7710f9506b69d603867": {
            "singleVisual": {
              "visualType": "image",
              "objects": {},
              "display": {
                "mode": "hidden"
              }
            }
          },
          "fcdbd8250abce6adda06": {
            "singleVisual": {
              "visualType": "actionButton",
              "objects": {}
            }
          }
        },
        "visualContainerGroups": {
          "6b3bbdd5a001d872900e": {
            "isHidden": false,
            "children": {
              "3c33159bbcd433b20003": {
                "isHidden": true
              },
              "b015c3ebd9bb65dc070b": {
                "isHidden": false
              }
            }
          },
          "6bd85a4e0b5bb4609767": {
            "isHidden": false
          }
        }
      }
    },
    "objects": {
      "merge": {
        "outspacePane": [
          {
            "properties": {
              "expanded": {
                "expr": {
                  "Literal": {
                    "Value": "false"
                  }
                }
              }
            }
          }
        ]
      }
    }
  }
}