{
  "$schema": "https://developer.microsoft.com/json-schemas/fabric/item/report/definition/bookmark/2.1.0/schema.json",
  "displayName": "Open Filter-Inventory Overview ",
  "name": "b4c5b22374de49be8a2dfef366838730",
  "options": {
    "targetVisualNames": [
      "e0ac157d089456001c2e",
      "482619b47200e590a2b5",
      "3d3ff89bb3b0383b4e42",
      "7374626477c39944ba07",
      "517df93b72508d1196e0",
      "19b2236e6e7179d06b7c",
      "07e2b4646a96e36c9264",
      "82a25b540e3e3361a111",
      "659edd7e180340ee7e63",
      "87703fdfe0ad1d3d6480",
      "76d677303e0d1445e698",
      "a0de9c9030a1084726c0",
      "8190ab2d7b8834a6bb18"
    ],
    "suppressActiveSection": true,
    "suppressData": true
  },
  "explorationState": {
    "version": "1.3",
    "activeSection": "8f51368399d682ec07c6",
    "sections": {
      "8f51368399d682ec07c6": {
        "visualContainers": {
          "066c60d482c925aa3d37": {
            "singleVisual": {
              "visualType": "image",
              "objects": {}
            }
          },
          "1e27f38635bc60946011": {
            "filters": {
              "byExpr": [
                {
                  "name": "b457d89462e4d172e918",
                  "type": "Advanced",
                  "expression": {
                    "Measure": {
                      "Expression": {
                        "SourceRef": {
                          "Entity": "03_inventoryMeasures"
                        }
                      },
                      "Property": "Traget Stock Health"
                    }
                  },
                  "howCreated": 0
                },
                {
                  "name": "c1383b915b8514672541",
                  "type": "Advanced",
                  "expression": {
                    "Measure": {
                      "Expression": {
                        "SourceRef": {
                          "Entity": "03_inventoryMeasures"
                        }
                      },
                      "Property": "Stock Health %"
                    }
                  },
                  "howCreated": 0
                }
              ]
            },
            "singleVisual": {
              "visualType": "gauge",
              "objects": {},
              "orderBy": [
                {
                  "Direction": 2,
                  "Expression": {
                    "Measure": {
                      "Expression": {
                        "SourceRef": {
                          "Entity": "03_inventoryMeasures"
                        }
                      },
                      "Property": "Stock Health %"
                    }
                  }
                }
              ]
            }
          },
          "447fbc2da8357361b7bf": {
            "filters": {
              "byExpr": [
                {
                  "name": "aad7139031405033db80",
                  "type": "Advanced",
                  "expression": {
                    "HierarchyLevel": {
                      "Expression": {
                        "Hierarchy": {
                          "Expression": {
                            "PropertyVariationSource": {
                              "Expression": {
                                "SourceRef": {
                                  "Entity": "dim_date"
                                }
                              },
                              "Name": "Variation",
                              "Property": "full_date"
                            }
                          },
                          "Hierarchy": "Date Hierarchy"
                        }
                      },
                      "Level": "Year"
                    }
                  },
                  "howCreated": 0
                },
                {
                  "name": "5d9d2d24d979eaa64454",
                  "type": "Categorical",
                  "expression": {
                    "HierarchyLevel": {
                      "Expression": {
                        "Hierarchy": {
                          "Expression": {
                            "PropertyVariationSource": {
                              "Expression": {
                                "SourceRef": {
                                  "Entity": "dim_date"
                                }
                              },
                              "Name": "Variation",
                              "Property": "full_date"
                            }
                          },
                          "Hierarchy": "Date Hierarchy"
                        }
                      },
                      "Level": "Quarter"
                    }
                  },
                  "howCreated": 0
                },
                {
                  "name": "cf65ca5c630d3d40a7b5",
                  "type": "Categorical",
                  "expression": {
                    "HierarchyLevel": {
                      "Expression": {
                        "Hierarchy": {
                          "Expression": {
                            "PropertyVariationSource": {
                              "Expression": {
                                "SourceRef": {
                                  "Entity": "dim_date"
                                }
                              },
                              "Name": "Variation",
                              "Property": "full_date"
                            }
                          },
                          "Hierarchy": "Date Hierarchy"
                        }
                      },
                      "Level": "Month"
                    }
                  },
                  "howCreated": 0
                },
                {
                  "name": "f61d23f035d976bb3a0b",
                  "type": "Advanced",
                  "expression": {
                    "HierarchyLevel": {
                      "Expression": {
                        "Hierarchy": {
                          "Expression": {
                            "PropertyVariationSource": {
                              "Expression": {
                                "SourceRef": {
                                  "Entity": "dim_date"
                                }
                              },
                              "Name": "Variation",
                              "Property": "full_date"
                            }
                          },
                          "Hierarchy": "Date Hierarchy"
                        }
                      },
                      "Level": "Day"
                    }
                  },
                  "howCreated": 0
                },
                {
                  "name": "2e2b1b0366566ead5780",
                  "type": "Advanced",
                  "expression": {
                    "Measure": {
                      "Expression": {
                        "SourceRef": {
                          "Entity": "03_inventoryMeasures"
                        }
                      },
                      "Property": "Total Reserved Qty"
                    }
                  },
                  "howCreated": 0
                },
                {
                  "name": "fc884264dbeb41776043",
                  "type": "Advanced",
                  "expression": {
                    "Measure": {
                      "Expression": {
                        "SourceRef": {
                          "Entity": "03_inventoryMeasures"
                        }
                      },
                      "Property": "Total On Hand"
                    }
                  },
                  "howCreated": 0
                },
                {
                  "name": "536c6b86b2e6b02046d3",
                  "type": "Advanced",
                  "expression": {
                    "Measure": {
                      "Expression": {
                        "SourceRef": {
                          "Entity": "03_inventoryMeasures"
                        }
                      },
                      "Property": "Total Available Qty"
                    }
                  },
                  "howCreated": 0
                }
              ]
            },
            "singleVisual": {
              "visualType": "lineChart",
              "objects": {},
              "activeProjections": {
                "Category": [
                  {
                    "HierarchyLevel": {
                      "Expression": {
                        "Hierarchy": {
                          "Expression": {
                            "PropertyVariationSource": {
                              "Expression": {
                                "SourceRef": {
                                  "Entity": "dim_date"
                                }
                              },
                              "Name": "Variation",
                              "Property": "full_date"
                            }
                          },
                          "Hierarchy": "Date Hierarchy"
                        }
                      },
                      "Level": "Year"
                    }
                  },
                  {
                    "HierarchyLevel": {
                      "Expression": {
                        "Hierarchy": {
                          "Expression": {
                            "PropertyVariationSource": {
                              "Expression": {
                                "SourceRef": {
                                  "Entity": "dim_date"
                                }
                              },
                              "Name": "Variation",
                              "Property": "full_date"
                            }
                          },
                          "Hierarchy": "Date Hierarchy"
                        }
                      },
                      "Level": "Quarter"
                    }
                  },
                  {
                    "HierarchyLevel": {
                      "Expression": {
                        "Hierarchy": {
                          "Expression": {
                            "PropertyVariationSource": {
                              "Expression": {
                                "SourceRef": {
                                  "Entity": "dim_date"
                                }
                              },
                              "Name": "Variation",
                              "Property": "full_date"
                            }
                          },
                          "Hierarchy": "Date Hierarchy"
                        }
                      },
                      "Level": "Month"
                    }
                  }
                ]
              }
            }
          },
          "4624b96cf8f44e7ca53f": {
            "filters": {
              "byExpr": [
                {
                  "name": "882e67d3793ee0e5dd6e",
                  "type": "Categorical",
                  "expression": {
                    "Column": {
                      "Expression": {
                        "SourceRef": {
                          "Entity": "fact_inventory"
                        }
                      },
                      "Property": "inventory_status"
                    }
                  },
                  "howCreated": 0
                },
                {
                  "name": "3db73b4605b2821b8db0",
                  "type": "Advanced",
                  "expression": {
                    "Aggregation": {
                      "Expression": {
                        "Column": {
                          "Expression": {
                            "SourceRef": {
                              "Entity": "fact_inventory"
                            }
                          },
                          "Property": "product_id"
                        }
                      },
                      "Function": 5
                    }
                  },
                  "howCreated": 0
                }
              ]
            },
            "singleVisual": {
              "visualType": "donutChart",
              "objects": {},
              "orderBy": [
                {
                  "Direction": 2,
                  "Expression": {
                    "Aggregation": {
                      "Expression": {
                        "Column": {
                          "Expression": {
                            "SourceRef": {
                              "Entity": "fact_inventory"
                            }
                          },
                          "Property": "product_id"
                        }
                      },
                      "Function": 5
                    }
                  }
                }
              ],
              "activeProjections": {
                "Category": [
                  {
                    "Column": {
                      "Expression": {
                        "SourceRef": {
                          "Entity": "fact_inventory"
                        }
                      },
                      "Property": "inventory_status"
                    }
                  }
                ]
              }
            }
          },
          "8f046dfec439b8706b21": {
            "singleVisual": {
              "visualType": "image",
              "objects": {}
            }
          },
          "ecd27dc1b7c1ed22860d": {
            "singleVisual": {
              "visualType": "shape",
              "objects": {}
            }
          },
          "910d57561acdf3eeb27f": {
            "filters": {
              "byExpr": [
                {
                  "name": "0f35b0e40a58be1d0ab0",
                  "type": "Advanced",
                  "expression": {
                    "Measure": {
                      "Expression": {
                        "SourceRef": {
                          "Entity": "03_inventoryMeasures"
                        }
                      },
                      "Property": "Total Inventory Value"
                    }
                  },
                  "howCreated": 0
                },
                {
                  "name": "5dfdd66c913e44a00a14",
                  "type": "Advanced",
                  "expression": {
                    "Measure": {
                      "Expression": {
                        "SourceRef": {
                          "Entity": "03_inventoryMeasures"
                        }
                      },
                      "Property": "Total On Hand"
                    }
                  },
                  "howCreated": 0
                },
                {
                  "name": "902ac9ff72048a101752",
                  "type": "Advanced",
                  "expression": {
                    "Measure": {
                      "Expression": {
                        "SourceRef": {
                          "Entity": "03_inventoryMeasures"
                        }
                      },
                      "Property": "Stock Health %"
                    }
                  },
                  "howCreated": 0
                },
                {
                  "name": "81cb732394103b423c58",
                  "type": "Advanced",
                  "expression": {
                    "Measure": {
                      "Expression": {
                        "SourceRef": {
                          "Entity": "03_inventoryMeasures"
                        }
                      },
                      "Property": "Low Stock Items"
                    }
                  },
                  "howCreated": 0
                },
                {
                  "name": "f3a480c29923b060d343",
                  "type": "Advanced",
                  "expression": {
                    "Measure": {
                      "Expression": {
                        "SourceRef": {
                          "Entity": "03_inventoryMeasures"
                        }
                      },
                      "Property": "Commitment Rate %"
                    }
                  },
                  "howCreated": 0
                }
              ]
            },
            "singleVisual": {
              "visualType": "cardVisual",
              "objects": {},
              "orderBy": [
                {
                  "Direction": 2,
                  "Expression": {
                    "Measure": {
                      "Expression": {
                        "SourceRef": {
                          "Entity": "03_inventoryMeasures"
                        }
                      },
                      "Property": "Total Inventory Value"
                    }
                  }
                }
              ]
            }
          },
          "1acc80d09b130d43588e": {
            "singleVisual": {
              "visualType": "actionButton",
              "objects": {}
            }
          },
          "4ef3a0916850540e95e4": {
            "singleVisual": {
              "visualType": "actionButton",
              "objects": {}
            }
          },
          "4fffb92a053c3e093539": {
            "singleVisual": {
              "visualType": "actionButton",
              "objects": {}
            }
          },
          "50bae9113e80cc9dde3b": {
            "singleVisual": {
              "visualType": "actionButton",
              "objects": {}
            }
          },
          "552b964f849868900b67": {
            "singleVisual": {
              "visualType": "actionButton",
              "objects": {}
            }
          },
          "55c749849b8a2a028d83": {
            "singleVisual": {
              "visualType": "actionButton",
              "objects": {}
            }
          },
          "7fe25e719d523ec50778": {
            "singleVisual": {
              "visualType": "actionButton",
              "objects": {}
            }
          },
          "823cebfd0e5606816e77": {
            "singleVisual": {
              "visualType": "actionButton",
              "objects": {}
            }
          },
          "896a99344e6a22e938ca": {
            "singleVisual": {
              "visualType": "actionButton",
              "objects": {}
            }
          },
          "92c4ebda02d91143ac59": {
            "singleVisual": {
              "visualType": "actionButton",
              "objects": {}
            }
          },
          "c70b93faa118a403ed01": {
            "singleVisual": {
              "visualType": "image",
              "objects": {}
            }
          },
          "e41c272db1022003bee0": {
            "singleVisual": {
              "visualType": "actionButton",
              "objects": {}
            }
          },
          "0d04af520ea7e51042e7": {
            "singleVisual": {
              "visualType": "actionButton",
              "objects": {}
            }
          },
          "1a2ead38735408792130": {
            "singleVisual": {
              "visualType": "actionButton",
              "objects": {}
            }
          },
          "32ecf7002547d020b0b0": {
            "singleVisual": {
              "visualType": "actionButton",
              "objects": {}
            }
          },
          "5d992623467b83b0abb6": {
            "singleVisual": {
              "visualType": "actionButton",
              "objects": {}
            }
          },
          "66a3bef66cb63b159025": {
            "singleVisual": {
              "visualType": "actionButton",
              "objects": {}
            }
          },
          "a2b9e210d31360536650": {
            "singleVisual": {
              "visualType": "actionButton",
              "objects": {}
            }
          },
          "a4e4dd6d9c61d529210a": {
            "singleVisual": {
              "visualType": "actionButton",
              "objects": {}
            }
          },
          "b22ac03497138020270b": {
            "singleVisual": {
              "visualType": "actionButton",
              "objects": {}
            }
          },
          "bcf66d365420c5591d00": {
            "singleVisual": {
              "visualType": "actionButton",
              "objects": {}
            }
          },
          "bfc517b26908302e9505": {
            "singleVisual": {
              "visualType": "actionButton",
              "objects": {}
            }
          },
          "c493f4e1e0ec18d2ca6b": {
            "singleVisual": {
              "visualType": "actionButton",
              "objects": {}
            }
          },
          "fdf30f5c60716a05c793": {
            "singleVisual": {
              "visualType": "image",
              "objects": {}
            }
          },
          "849740d08e9c7c838a88": {
            "singleVisual": {
              "visualType": "shape",
              "objects": {}
            }
          },
          "d4ef596b0cc308929a53": {
            "singleVisual": {
              "visualType": "image",
              "objects": {}
            }
          },
          "f66774e6c060a08e89ea": {
            "singleVisual": {
              "visualType": "actionButton",
              "objects": {}
            }
          },
          "d9984d6b7148789bc0b9": {
            "singleVisual": {
              "visualType": "textbox",
              "objects": {}
            }
          },
          "f3422bede30c4dbff5a7": {
            "filters": {
              "byExpr": [
                {
                  "name": "05012a4627827c1db0bc",
                  "type": "Advanced",
                  "expression": {
                    "Measure": {
                      "Expression": {
                        "SourceRef": {
                          "Entity": "Last Refresh"
                        }
                      },
                      "Property": "Last Refresh"
                    }
                  },
                  "howCreated": 0
                }
              ]
            },
            "singleVisual": {
              "visualType": "cardVisual",
              "objects": {}
            }
          },
          "cb31d2e91ca85b8a3a62": {
            "filters": {
              "byExpr": [
                {
                  "name": "14ba980f2d0e4e909500",
                  "type": "Categorical",
                  "expression": {
                    "Column": {
                      "Expression": {
                        "SourceRef": {
                          "Entity": "dim_warehouse"
                        }
                      },
                      "Property": "warehouse_name"
                    }
                  },
                  "howCreated": 0
                },
                {
                  "name": "c4f2f583e04a912a96bc",
                  "type": "Advanced",
                  "expression": {
                    "Measure": {
                      "Expression": {
                        "SourceRef": {
                          "Entity": "03_inventoryMeasures"
                        }
                      },
                      "Property": "Total Reserved Qty"
                    }
                  },
                  "howCreated": 0
                },
                {
                  "name": "b21b41460847d83a16c2",
                  "type": "Advanced",
                  "expression": {
                    "Measure": {
                      "Expression": {
                        "SourceRef": {
                          "Entity": "03_inventoryMeasures"
                        }
                      },
                      "Property": "Total On Hand"
                    }
                  },
                  "howCreated": 0
                },
                {
                  "name": "988ee5b1b8ab2eba1225",
                  "type": "Advanced",
                  "expression": {
                    "Measure": {
                      "Expression": {
                        "SourceRef": {
                          "Entity": "03_inventoryMeasures"
                        }
                      },
                      "Property": "Total Available Qty"
                    }
                  },
                  "howCreated": 0
                }
              ]
            },
            "singleVisual": {
              "visualType": "clusteredColumnChart",
              "objects": {},
              "orderBy": [
                {
                  "Direction": 2,
                  "Expression": {
                    "Measure": {
                      "Expression": {
                        "SourceRef": {
                          "Entity": "03_inventoryMeasures"
                        }
                      },
                      "Property": "Total Reserved Qty"
                    }
                  }
                }
              ],
              "activeProjections": {
                "Category": [
                  {
                    "Column": {
                      "Expression": {
                        "SourceRef": {
                          "Entity": "dim_warehouse"
                        }
                      },
                      "Property": "warehouse_name"
                    }
                  }
                ]
              }
            }
          },
          "e0ac157d089456001c2e": {
            "singleVisual": {
              "visualType": "image",
              "objects": {},
              "display": {
                "mode": "hidden"
              }
            }
          },
          "482619b47200e590a2b5": {
            "singleVisual": {
              "visualType": "image",
              "objects": {}
            }
          },
          "07e2b4646a96e36c9264": {
            "filters": {
              "byExpr": [
                {
                  "name": "dacd62c0be9a343ea0ce",
                  "type": "Categorical",
                  "filter": {
                    "Version": 2,
                    "From": [
                      {
                        "Name": "d",
                        "Entity": "dim_product",
                        "Type": 0
                      }
                    ],
                    "Where": [
                      {
                        "Condition": {
                          "Not": {
                            "Expression": {
                              "In": {
                                "Expressions": [
                                  {
                                    "Column": {
                                      "Expression": {
                                        "SourceRef": {
                                          "Source": "d"
                                        }
                                      },
                                      "Property": "product_type"
                                    }
                                  }
                                ],
                                "Values": [
                                  [
                                    {
                                      "Literal": {
                                        "Value": "null"
                                      }
                                    }
                                  ]
                                ]
                              }
                            }
                          }
                        }
                      }
                    ]
                  },
                  "expression": {
                    "Column": {
                      "Expression": {
                        "SourceRef": {
                          "Entity": "dim_product"
                        }
                      },
                      "Property": "product_type"
                    }
                  },
                  "howCreated": 0
                }
              ]
            },
            "singleVisual": {
              "visualType": "slicer",
              "objects": {
                "merge": {
                  "data": [
                    {
                      "properties": {
                        "mode": {
                          "expr": {
                            "Literal": {
                              "Value": "'Dropdown'"
                            }
                          }
                        }
                      }
                    }
                  ]
                }
              },
              "activeProjections": {
                "Values": [
                  {
                    "Column": {
                      "Expression": {
                        "SourceRef": {
                          "Entity": "dim_product"
                        }
                      },
                      "Property": "product_type"
                    }
                  }
                ]
              }
            }
          },
          "82a25b540e3e3361a111": {
            "filters": {
              "byExpr": [
                {
                  "name": "30f2ecc58859953b3903",
                  "type": "Categorical",
                  "filter": {
                    "Version": 2,
                    "From": [
                      {
                        "Name": "d",
                        "Entity": "dim_partner",
                        "Type": 0
                      }
                    ],
                    "Where": [
                      {
                        "Condition": {
                          "Not": {
                            "Expression": {
                              "In": {
                                "Expressions": [
                                  {
                                    "Column": {
                                      "Expression": {
                                        "SourceRef": {
                                          "Source": "d"
                                        }
                                      },
                                      "Property": "partner_name"
                                    }
                                  }
                                ],
                                "Values": [
                                  [
                                    {
                                      "Literal": {
                                        "Value": "null"
                                      }
                                    }
                                  ]
                                ]
                              }
                            }
                          }
                        }
                      }
                    ]
                  },
                  "expression": {
                    "Column": {
                      "Expression": {
                        "SourceRef": {
                          "Entity": "dim_partner"
                        }
                      },
                      "Property": "partner_name"
                    }
                  },
                  "howCreated": 0
                }
              ]
            },
            "singleVisual": {
              "visualType": "slicer",
              "objects": {
                "merge": {
                  "data": [
                    {
                      "properties": {
                        "mode": {
                          "expr": {
                            "Literal": {
                              "Value": "'Dropdown'"
                            }
                          }
                        }
                      }
                    }
                  ]
                }
              },
              "activeProjections": {
                "Values": [
                  {
                    "Column": {
                      "Expression": {
                        "SourceRef": {
                          "Entity": "dim_partner"
                        }
                      },
                      "Property": "partner_name"
                    }
                  }
                ]
              }
            }
          },
          "659edd7e180340ee7e63": {
            "singleVisual": {
              "visualType": "image",
              "objects": {}
            }
          },
          "87703fdfe0ad1d3d6480": {
            "filters": {
              "byExpr": [
                {
                  "name": "eae5b2d05c7bc2ad0dc2",
                  "type": "Categorical",
                  "filter": {
                    "Version": 2,
                    "From": [
                      {
                        "Name": "d",
                        "Entity": "dim_product",
                        "Type": 0
                      }
                    ],
                    "Where": [
                      {
                        "Condition": {
                          "Not": {
                            "Expression": {
                              "In": {
                                "Expressions": [
                                  {
                                    "Column": {
                                      "Expression": {
                                        "SourceRef": {
                                          "Source": "d"
                                        }
                                      },
                                      "Property": "categ_name"
                                    }
                                  }
                                ],
                                "Values": [
                                  [
                                    {
                                      "Literal": {
                                        "Value": "null"
                                      }
                                    }
                                  ]
                                ]
                              }
                            }
                          }
                        }
                      }
                    ]
                  },
                  "expression": {
                    "Column": {
                      "Expression": {
                        "SourceRef": {
                          "Entity": "dim_product"
                        }
                      },
                      "Property": "categ_name"
                    }
                  },
                  "howCreated": 0
                }
              ]
            },
            "singleVisual": {
              "visualType": "slicer",
              "objects": {
                "merge": {
                  "data": [
                    {
                      "properties": {
                        "mode": {
                          "expr": {
                            "Literal": {
                              "Value": "'Dropdown'"
                            }
                          }
                        }
                      }
                    }
                  ]
                }
              },
              "activeProjections": {
                "Values": [
                  {
                    "Column": {
                      "Expression": {
                        "SourceRef": {
                          "Entity": "dim_product"
                        }
                      },
                      "Property": "categ_name"
                    }
                  }
                ]
              }
            }
          },
          "76d677303e0d1445e698": {
            "singleVisual": {
              "visualType": "actionButton",
              "objects": {}
            }
          },
          "a0de9c9030a1084726c0": {
            "singleVisual": {
              "visualType": "shape",
              "objects": {}
            }
          },
          "8190ab2d7b8834a6bb18": {
            "filters": {
              "byExpr": [
                {
                  "name": "4567d722ea1a162529d8",
                  "type": "Categorical",
                  "filter": {
                    "Version": 2,
                    "From": [
                      {
                        "Name": "d",
                        "Entity": "dim_product",
                        "Type": 0
                      }
                    ],
                    "Where": [
                      {
                        "Condition": {
                          "Not": {
                            "Expression": {
                              "In": {
                                "Expressions": [
                                  {
                                    "Column": {
                                      "Expression": {
                                        "SourceRef": {
                                          "Source": "d"
                                        }
                                      },
                                      "Property": "product_name"
                                    }
                                  }
                                ],
                                "Values": [
                                  [
                                    {
                                      "Literal": {
                                        "Value": "null"
                                      }
                                    }
                                  ]
                                ]
                              }
                            }
                          }
                        }
                      }
                    ]
                  },
                  "expression": {
                    "Column": {
                      "Expression": {
                        "SourceRef": {
                          "Entity": "dim_product"
                        }
                      },
                      "Property": "product_name"
                    }
                  },
                  "howCreated": 0
                }
              ]
            },
            "singleVisual": {
              "visualType": "slicer",
              "objects": {
                "merge": {
                  "data": [
                    {
                      "properties": {
                        "mode": {
                          "expr": {
                            "Literal": {
                              "Value": "'Dropdown'"
                            }
                          }
                        }
                      }
                    }
                  ]
                }
              },
              "activeProjections": {
                "Values": [
                  {
                    "Column": {
                      "Expression": {
                        "SourceRef": {
                          "Entity": "dim_product"
                        }
                      },
                      "Property": "product_name"
                    }
                  }
                ]
              }
            }
          },
          "517df93b72508d1196e0": {
            "singleVisual": {
              "visualType": "image",
              "objects": {}
            }
          },
          "19b2236e6e7179d06b7c": {
            "filters": {
              "byExpr": [
                {
                  "name": "f1bcc0ce1bee2d343571",
                  "type": "Categorical",
                  "expression": {
                    "Column": {
                      "Expression": {
                        "SourceRef": {
                          "Entity": "dim_date"
                        }
                      },
                      "Property": "full_date"
                    }
                  },
                  "howCreated": 0
                }
              ]
            },
            "singleVisual": {
              "visualType": "PBINathanDateRangeSlicer2024A1B2C3D4E5F6",
              "objects": {},
              "orderBy": [
                {
                  "Direction": 1,
                  "Expression": {
                    "Column": {
                      "Expression": {
                        "SourceRef": {
                          "Entity": "dim_date"
                        }
                      },
                      "Property": "full_date"
                    }
                  }
                }
              ]
            }
          }
        },
        "visualContainerGroups": {
          "5936a5a105ee95a45399": {
            "isHidden": true
          },
          "9629b0d06aee324c09d2": {
            "isHidden": true,
            "children": {
              "0d723ef333d90975b1b1": {
                "isHidden": true
              }
            }
          },
          "7374626477c39944ba07": {
            "isHidden": false
          },
          "3d3ff89bb3b0383b4e42": {
            "isHidden": true
          }
        }
      }
    },
    "objects": {
      "merge": {
        "outspacePane": [
          {
            "properties": {
              "expanded": {
                "expr": {
                  "Literal": {
                    "Value": "false"
                  }
                }
              }
            }
          }
        ]
      }
    }
  }
}